LICENSE
MANIFEST.in
README.rst
setup.py
admin_daterange_filter/__init__.py
admin_daterange_filter/filter.py
admin_daterange_filter/locale/zh_CN/LC_MESSAGES/django.mo
admin_daterange_filter/locale/zh_CN/LC_MESSAGES/django.po
admin_daterange_filter/static/admin_daterange_filter/themes/base/jquery-ui.css
admin_daterange_filter/static/admin_daterange_filter/themes/base/jquery.ui.accordion.css
admin_daterange_filter/static/admin_daterange_filter/themes/base/jquery.ui.all.css
admin_daterange_filter/static/admin_daterange_filter/themes/base/jquery.ui.autocomplete.css
admin_daterange_filter/static/admin_daterange_filter/themes/base/jquery.ui.base.css
admin_daterange_filter/static/admin_daterange_filter/themes/base/jquery.ui.button.css
admin_daterange_filter/static/admin_daterange_filter/themes/base/jquery.ui.core.css
admin_daterange_filter/static/admin_daterange_filter/themes/base/jquery.ui.datepicker.css
admin_daterange_filter/static/admin_daterange_filter/themes/base/jquery.ui.dialog.css
admin_daterange_filter/static/admin_daterange_filter/themes/base/jquery.ui.menu.css
admin_daterange_filter/static/admin_daterange_filter/themes/base/jquery.ui.progressbar.css
admin_daterange_filter/static/admin_daterange_filter/themes/base/jquery.ui.resizable.css
admin_daterange_filter/static/admin_daterange_filter/themes/base/jquery.ui.selectable.css
admin_daterange_filter/static/admin_daterange_filter/themes/base/jquery.ui.slider.css
admin_daterange_filter/static/admin_daterange_filter/themes/base/jquery.ui.spinner.css
admin_daterange_filter/static/admin_daterange_filter/themes/base/jquery.ui.tabs.css
admin_daterange_filter/static/admin_daterange_filter/themes/base/jquery.ui.theme.css
admin_daterange_filter/static/admin_daterange_filter/themes/base/jquery.ui.tooltip.css
admin_daterange_filter/static/admin_daterange_filter/themes/base/images/ui-bg_flat_0_aaaaaa_40x100.png
admin_daterange_filter/static/admin_daterange_filter/themes/base/images/ui-bg_flat_75_ffffff_40x100.png
django_admin_daterange_filter.egg-info/PKG-INFO
django_admin_daterange_filter.egg-info/SOURCES.txt
django_admin_daterange_filter.egg-info/dependency_links.txt
django_admin_daterange_filter.egg-info/not-zip-safe
django_admin_daterange_filter.egg-info/top_level.txt