Metadata-Version: 1.1
Name: django-admin-daterange-filter
Version: 0.1.3
Summary: daterange-filter for django admin used by jquery.datepicker
Home-page: https://github.com/nieoding/django-admin-daterange-filter
Author: nieo ding
Author-email: dingzh@66wifi.com
License: BSD License
Platform: UNKNOWN
Classifier: Environment :: Web Environment
Classifier: Framework :: Django
Classifier: Intended Audience :: Developers
Classifier: License :: OSI Approved :: BSD License
Classifier: Operating System :: OS Independent
Classifier: Programming Language :: Python
Classifier: Programming Language :: Python :: 2.7
Classifier: Topic :: Internet :: WWW/HTTP
Classifier: Topic :: Internet :: WWW/HTTP :: Dynamic Content
